metaloci/__init__.py
metaloci/__main__.py
metaloci/mlo.py
metaloci/graph_layout/__init__.py
metaloci/graph_layout/kk.py
metaloci/misc/__init__.py
metaloci/misc/misc.py
metaloci/plot/__init__.py
metaloci/plot/plot.py
metaloci/spatial_stats/__init__.py
metaloci/spatial_stats/lmi.py
metaloci/tests/__init__.py
metaloci/tests/test_tools.py
metaloci/tests/data/aggregate.txt
metaloci/tests/data/gencode.vM35.annotation_chr19.gtf.gz
metaloci/tests/data/mm39_chrom_sizes.txt
metaloci/tests/data/regions_test.txt
metaloci/tests/data/signals_test.txt
metaloci/tests/data/hic/ICE_DM_5kb_eef0283c05_chr19.mcool
metaloci/tests/data/signal/DM_27me3-merged-sub137930236_chr19.bed
metaloci/tests/data/signal/DM_27me3-merged-sub137930236_chr19_header.bed
metaloci/tests/data/signal/DM_Arid1a-sub17717303_15052021_chr19.bed
metaloci/tests/data/signal/DM_Arid1a-sub17717303_15052021_chr19_header.bed
metaloci/tests/data/signal/mm39_organoid_ATAC_4000.bed
metaloci/tests/data/signal/mm39_organoid_ATAC_4000_chr19.bed
metaloci/tests/data/signal/multi_chr19.bed
metaloci/tools/__init__.py
metaloci/tools/figure.py
metaloci/tools/layout.py
metaloci/tools/ml.py
metaloci/tools/prep.py
metaloci/tools/scan.py
metaloci/utility_scripts/__init__.py
metaloci/utility_scripts/bts.py
metaloci/utility_scripts/compressor.py
metaloci/utility_scripts/gene_selector.py
metaloci/utility_scripts/sniffer.py
metaloci-1.3.3.dist-info/licenses/LICENSE
metaloci-1.3.3.dist-info/METADATA
metaloci-1.3.3.dist-info/WHEEL
metaloci-1.3.3.dist-info/entry_points.txt
metaloci-1.3.3.dist-info/top_level.txt
metaloci-1.3.3.dist-info/RECORD
