Metadata-Version: 2.4
Name: metaloci
Version: 1.3.3
Summary: METALoci: spatially auto-correlated signals in 3D genomes
Home-page: https://github.com/3DGenomes/METALoci/
Author: Leo Zuber, Iago Maceda, Juan Antonio Rodríguez and Marc Martí-Renom
Author-email: martirenom@cnag.eu
Classifier: Programming Language :: Python :: 3.12
Classifier: License :: OSI Approved :: GNU General Public License v3 (GPLv3)
Classifier: Topic :: Scientific/Engineering :: Bio-Informatics
Classifier: Operating System :: POSIX :: Linux
License-File: LICENSE
Requires-Dist: docutils<0.21
Requires-Dist: adjustText==1.1.1
Requires-Dist: bioframe
Requires-Dist: cooler==0.9.2
Requires-Dist: dill==0.3.8
Requires-Dist: esda==2.7.0
Requires-Dist: geopandas==0.13.2
Requires-Dist: h5py==3.10.0
Requires-Dist: hic-straw==1.3.1
Requires-Dist: imageio==2.37.0
Requires-Dist: imageio-ffmpeg==0.6.0
Requires-Dist: libpysal==4.13.0
Requires-Dist: matplotlib==3.7.2
Requires-Dist: networkx==3.1
Requires-Dist: numba==0.61.2
Requires-Dist: numpy==1.26.4
Requires-Dist: pandas==2.0.3
Requires-Dist: pillow==10.3.0
Requires-Dist: pybedtools==0.9.1
Requires-Dist: scipy==1.16.1
Requires-Dist: seaborn==0.11.0
Requires-Dist: setuptools<81,>78.1.1
Requires-Dist: shapely==2.1.1
Requires-Dist: sphinx-rtd-theme==2.0.0
Requires-Dist: sphinx==7.3.7
Requires-Dist: tqdm==4.66.3
Requires-Dist: sphinx-argparse
Requires-Dist: cppy>=1.2.0
Dynamic: author
Dynamic: author-email
Dynamic: classifier
Dynamic: description
Dynamic: description-content-type
Dynamic: home-page
Dynamic: license-file
Dynamic: requires-dist
Dynamic: summary
